index2rc/__init__.py
index2rc-1.0.1.dist-info/METADATA
index2rc-1.0.1.dist-info/WHEEL
index2rc-1.0.1.dist-info/entry_points.txt
index2rc-1.0.1.dist-info/top_level.txt
index2rc-1.0.1.dist-info/RECORD
